chia/__init__.py
chia/__main__.py
chia/_tests/README.md
chia/_tests/__init__.py
chia/_tests/blockchain/__init__.py
chia/_tests/blockchain/blockchain_test_utils.py
chia/_tests/blockchain/config.py
chia/_tests/blockchain/test_augmented_chain.py
chia/_tests/blockchain/test_blockchain.py
chia/_tests/blockchain/test_blockchain_transactions.py
chia/_tests/blockchain/test_build_chains.py
chia/_tests/blockchain/test_get_block_generator.py
chia/_tests/blockchain/test_lookup_fork_chain.py
chia/_tests/build-init-files.py
chia/_tests/build-job-matrix.py
chia/_tests/check_pytest_monitor_output.py
chia/_tests/check_sql_statements.py
chia/_tests/chia-start-sim
chia/_tests/clvm/__init__.py
chia/_tests/clvm/benchmark_costs.py
chia/_tests/clvm/coin_store.py
chia/_tests/clvm/test_chialisp_deserialization.py
chia/_tests/clvm/test_clvm_step.py
chia/_tests/clvm/test_curry_and_treehash.py
chia/_tests/clvm/test_message_conditions.py
chia/_tests/clvm/test_program.py
chia/_tests/clvm/test_puzzle_compression.py
chia/_tests/clvm/test_puzzle_drivers.py
chia/_tests/clvm/test_puzzles.py
chia/_tests/clvm/test_singletons.py
chia/_tests/clvm/test_spend_sim.py
chia/_tests/cmds/__init__.py
chia/_tests/cmds/cmd_test_utils.py
chia/_tests/cmds/config.py
chia/_tests/cmds/conftest.py
chia/_tests/cmds/test_click_types.py
chia/_tests/cmds/test_cmd_framework.py
chia/_tests/cmds/test_cmds_util.py
chia/_tests/cmds/test_daemon.py
chia/_tests/cmds/test_dev_gh.py
chia/_tests/cmds/test_farm_cmd.py
chia/_tests/cmds/test_show.py
chia/_tests/cmds/test_sim.py
chia/_tests/cmds/test_timelock_args.py
chia/_tests/cmds/test_tx_config_args.py
chia/_tests/cmds/testing_classes.py
chia/_tests/cmds/wallet/__init__.py
chia/_tests/cmds/wallet/test_consts.py
chia/_tests/cmds/wallet/test_did.py
chia/_tests/cmds/wallet/test_nft.py
chia/_tests/cmds/wallet/test_notifications.py
chia/_tests/cmds/wallet/test_offer.toffer
chia/_tests/cmds/wallet/test_tx_decorators.py
chia/_tests/cmds/wallet/test_vcs.py
chia_blockchain-2.5.7.dist-info/METADATA
chia_blockchain-2.5.7.dist-info/WHEEL
chia_blockchain-2.5.7.dist-info/entry_points.txt
chia_blockchain-2.5.7.dist-info/licenses/LICENSE
chia_blockchain-2.5.7.dist-info/RECORD
