Metadata-Version: 2.4
Name: chia-blockchain
Version: 2.5.7
Summary: Chia blockchain full node, farmer, timelord, and wallet.
License-Expression: Apache-2.0
License-File: LICENSE
Keywords: chia,blockchain,node
Author: Mariano Sorgente
Author-email: mariano@chia.net
Requires-Python: >=3.10, <4
Classifier: Programming Language :: Python :: 3
Classifier: Programming Language :: Python :: 3.10
Classifier: Programming Language :: Python :: 3.11
Classifier: Programming Language :: Python :: 3.12
Classifier: Programming Language :: Python :: 3.13
Classifier: Programming Language :: Python :: 3.14
Provides-Extra: dev
Provides-Extra: legacy-keyring
Provides-Extra: upnp
Requires-Dist: aiofiles (>=24.1.0)
Requires-Dist: aiohttp (>=3.10.4)
Requires-Dist: aiohttp_cors ; extra == "dev"
Requires-Dist: aiosqlite (>=0.20.0)
Requires-Dist: anyio (>=4.6.2.post1)
Requires-Dist: bitstring (>=4.1.4)
Requires-Dist: boto3 (>=1.35.43)
Requires-Dist: build ; extra == "dev"
Requires-Dist: chia-puzzles-py (>=0.20.1)
Requires-Dist: chia_rs (>=0.30,<0.31)
Requires-Dist: chiabip158 (>=1.5.2)
Requires-Dist: chiapos (>=2.0.10)
Requires-Dist: chiavdf (>=1.1.10)
Requires-Dist: click (>=8.1.7)
Requires-Dist: clvm (>=0.9.14)
Requires-Dist: clvm_tools (>=0.4.9)
Requires-Dist: clvm_tools_rs (>=0.1.45)
Requires-Dist: colorama (>=0.4.6)
Requires-Dist: colorlog (>=6.9.0)
Requires-Dist: concurrent_log_handler (>=0.9.25)
Requires-Dist: coverage ; extra == "dev"
Requires-Dist: cryptography (>=43.0.1)
Requires-Dist: diff-cover ; extra == "dev"
Requires-Dist: dnslib (>=0.9.25)
Requires-Dist: dnspython (>=2.6.1)
Requires-Dist: filelock (>=3.16.1)
Requires-Dist: hsms (>=0.3.1)
Requires-Dist: importlib-resources (>=6.4.5)
Requires-Dist: keyring (>=25.5.0)
Requires-Dist: keyrings.cryptfile ; extra == "legacy-keyring"
Requires-Dist: lxml ; extra == "dev"
Requires-Dist: miniupnpc ; extra == "upnp"
Requires-Dist: mypy ; extra == "dev"
Requires-Dist: packaging (>=24.0)
Requires-Dist: pip (>=24.2)
Requires-Dist: pre-commit ; extra == "dev"
Requires-Dist: psutil (>=6.1.0)
Requires-Dist: py3createtorrent ; extra == "dev"
Requires-Dist: pyinstaller ; extra == "dev"
Requires-Dist: pytest ; extra == "dev"
Requires-Dist: pytest-cov ; extra == "dev"
Requires-Dist: pytest-mock ; extra == "dev"
Requires-Dist: pytest-monitor ; extra == "dev"
Requires-Dist: pytest-xdist ; extra == "dev"
Requires-Dist: pyyaml (>=6.0.2)
Requires-Dist: ruff ; extra == "dev"
Requires-Dist: setproctitle (>=1.3.3)
Requires-Dist: setuptools (>=75.5.0)
Requires-Dist: sortedcontainers (>=2.4.0)
Requires-Dist: tach ; extra == "dev"
Requires-Dist: types-aiofiles ; extra == "dev"
Requires-Dist: types-cryptography ; extra == "dev"
Requires-Dist: types-pyyaml ; extra == "dev"
Requires-Dist: types-setuptools ; extra == "dev"
Requires-Dist: typing-extensions (>=4.12.2)
Requires-Dist: watchdog (>=4.0.1)
Requires-Dist: zstd (>=1.5.5.1) ; python_version < "3.12"
Requires-Dist: zstd (>=1.5.5.1) ; python_version == "3.12"
Project-URL: changelog, https://github.com/Chia-Network/chia-blockchain/blob/main/CHANGELOG.md
Project-URL: source, https://github.com/Chia-Network/chia-blockchain/
